{
  "name": "ACR Games",
  "slug": "acr-games",
  "country": "Ireland",
  "bonus": "First Deposit 125% up to $500 + 300 Free Spins",
  "rating": 4.3,
  "revenueRank": null,
  "spins": 23,
  "providers": [
    "NextGen",
    "Blueprint Gaming",
    "Thunderkick",
    "Genesis Gaming",
    "Big Time Gaming",
    "WMS",
    "Novomatic",
    "Arrows Edge"
  ],
  "likes": 1066,
  "comments": 268,
  "operatingCountries": [
    "Poland",
    "Netherlands"
  ],
  "createdAt": "2026-03-25T21:26:20.499864+00:00",
  "updatedAt": "2026-03-25T21:26:20.499864+00:00",
  "imageUrl": "https://picsum.photos/380/260?random=70",
  "avatarUrl": "https://api.dicebear.com/7.x/avataaars/svg?seed=acr-games",
  "imageGallery": [
    "https://picsum.photos/380/260?random=70",
    "https://picsum.photos/380/260?random=71",
    "https://picsum.photos/380/260?random=72",
    "https://picsum.photos/380/260?random=73"
  ]
}