{
  "name": "HashLucky Slots",
  "slug": "hashlucky-slots",
  "country": "Finland",
  "bonus": "VIP Bonus 150% up to $50",
  "rating": 3.8,
  "revenueRank": 20,
  "spins": 489,
  "providers": [
    "Arrows Edge",
    "Saucify"
  ],
  "likes": 1291,
  "comments": 340,
  "operatingCountries": [
    "Poland",
    "Australia",
    "Finland",
    "Portugal",
    "Ireland"
  ],
  "createdAt": "2026-03-25T21:26:20.499864+00:00",
  "updatedAt": "2026-03-25T21:26:20.499864+00:00",
  "imageUrl": "https://picsum.photos/380/260?random=144",
  "avatarUrl": "https://api.dicebear.com/7.x/avataaars/svg?seed=hashlucky-slots",
  "imageGallery": [
    "https://picsum.photos/380/260?random=144",
    "https://picsum.photos/380/260?random=145",
    "https://picsum.photos/380/260?random=146",
    "https://picsum.photos/380/260?random=147"
  ]
}