{
  "name": "Casino Mate Slots",
  "slug": "casino-mate-slots",
  "country": "Poland",
  "bonus": "Welcome Bonus 150% up to $100",
  "rating": 3.5,
  "revenueRank": null,
  "spins": 364,
  "providers": [
    "Habanero Systems",
    "Saucify",
    "Greentube"
  ],
  "likes": 806,
  "comments": 233,
  "operatingCountries": [
    "Poland",
    "Belgium",
    "Norway",
    "Finland",
    "Ireland"
  ],
  "createdAt": "2026-03-25T21:26:20.499864+00:00",
  "updatedAt": "2026-03-25T21:26:20.499864+00:00",
  "imageUrl": "https://picsum.photos/380/260?random=52",
  "avatarUrl": "https://api.dicebear.com/7.x/avataaars/svg?seed=casino-mate-slots",
  "imageGallery": [
    "https://picsum.photos/380/260?random=52",
    "https://picsum.photos/380/260?random=53",
    "https://picsum.photos/380/260?random=54"
  ]
}