{
  "name": "CoinKings Casino",
  "slug": "coinkings-casino",
  "country": "Poland",
  "bonus": "No Deposit 20 Free Spins",
  "rating": 3.6,
  "revenueRank": null,
  "spins": 318,
  "providers": [
    "1x2gaming",
    "Yggdrasil"
  ],
  "likes": 1227,
  "comments": 70,
  "operatingCountries": [
    "Netherlands",
    "Norway",
    "Spain",
    "Morocco"
  ],
  "createdAt": "2026-03-25T21:26:20.499864+00:00",
  "updatedAt": "2026-03-25T21:26:20.499864+00:00",
  "imageUrl": "https://picsum.photos/380/260?random=176",
  "avatarUrl": "https://api.dicebear.com/7.x/avataaars/svg?seed=coinkings-casino",
  "imageGallery": [
    "https://picsum.photos/380/260?random=176",
    "https://picsum.photos/380/260?random=177",
    "https://picsum.photos/380/260?random=178",
    "https://picsum.photos/380/260?random=179"
  ]
}