{
  "name": "Blaze Spins Casino",
  "slug": "blaze-spins-casino",
  "country": "Australia",
  "bonus": "First Deposit 50% up to $50 + 250 Free Spins",
  "rating": 3.9,
  "revenueRank": null,
  "spins": 0,
  "providers": [
    "BetSoft",
    "Quickspin",
    "Merkur",
    "Rival",
    "Genesis Gaming",
    "Blueprint Gaming",
    "Microgaming"
  ],
  "likes": 1573,
  "comments": 314,
  "operatingCountries": [
    "Netherlands"
  ],
  "createdAt": "2026-03-25T21:26:20.499864+00:00",
  "updatedAt": "2026-03-25T21:26:20.499864+00:00",
  "imageUrl": "https://picsum.photos/380/260?random=54",
  "avatarUrl": "https://api.dicebear.com/7.x/avataaars/svg?seed=blaze-spins-casino",
  "imageGallery": [
    "https://picsum.photos/380/260?random=54",
    "https://picsum.photos/380/260?random=55",
    "https://picsum.photos/380/260?random=56",
    "https://picsum.photos/380/260?random=57",
    "https://picsum.photos/380/260?random=58"
  ]
}